cryptease/__init__.py
cryptease/__version__.py
cryptease/compat/__init__.py
cryptease/compat/pickle/__init__.py
cryptease-0.2.0.data/scripts/crypt.py
cryptease-0.2.0.data/scripts/keyring.py
cryptease-0.2.0.dist-info/LICENSE
cryptease-0.2.0.dist-info/METADATA
cryptease-0.2.0.dist-info/WHEEL
cryptease-0.2.0.dist-info/top_level.txt
cryptease-0.2.0.dist-info/RECORD
